setup.cfg
setup.py
Easy_Args.egg-info/PKG-INFO
Easy_Args.egg-info/SOURCES.txt
Easy_Args.egg-info/dependency_links.txt
Easy_Args.egg-info/top_level.txt
easy_args/__init__.py
easy_args/decorators.py
easy_args/example.py
easy_args/helpers.py
easy_args/parsers.py
easy_args.egg-info/SOURCES.txt