Metadata-Version: 1.1
Name: easy-args
Version: 0.2
Summary: Get system parameters easily
Home-page: https://github.com/tatterdemalion/easy_args
Author: Can Mustafa Ozdemir
Author-email: canmustafaozdemir@gmail.com
License: UNKNOWN
Download-URL: https://github.com/tatterdemalion/easy_args/tarball/0.2
Platform: UNKNOWN
